ndimreg/__init__.py
ndimreg/__main__.py
ndimreg/_version.py
ndimreg/main.py
ndimreg/benchmark/__init__.py
ndimreg/benchmark/parameters.py
ndimreg/benchmark/result.py
ndimreg/benchmark/runner.py
ndimreg/benchmark/transformation.py
ndimreg/cli/__init__.py
ndimreg/cli/_common.py
ndimreg/cli/_types.py
ndimreg/cli/benchmark.py
ndimreg/cli/debug.py
ndimreg/cli/register.py
ndimreg/cli/tools.py
ndimreg/cli/transform.py
ndimreg/fusion/__init__.py
ndimreg/fusion/base.py
ndimreg/fusion/merge.py
ndimreg/fusion/protocol.py
ndimreg/image/__init__.py
ndimreg/image/image.py
ndimreg/image/image2d.py
ndimreg/image/image3d.py
ndimreg/image/loader.py
ndimreg/image/utils.py
ndimreg/processor/__init__.py
ndimreg/processor/bandpass.py
ndimreg/processor/base.py
ndimreg/processor/grayscale.py
ndimreg/processor/protocol.py
ndimreg/processor/rescale.py
ndimreg/processor/resize.py
ndimreg/processor/threshold.py
ndimreg/processor/window.py
ndimreg/processor/zoomer.py
ndimreg/registration/__init__.py
ndimreg/registration/base.py
ndimreg/registration/imregdft_2d.py
ndimreg/registration/keller_2d.py
ndimreg/registration/keller_2d_utils.py
ndimreg/registration/keller_3d.py
ndimreg/registration/protocol.py
ndimreg/registration/result.py
ndimreg/registration/rotation_axis_3d.py
ndimreg/registration/scikit_2d.py
ndimreg/registration/shift_resolver.py
ndimreg/registration/translation_fft_2d.py
ndimreg/registration/translation_fft_3d.py
ndimreg/tools/pseudo_polar_coordinates.py
ndimreg/transform/__init__.py
ndimreg/transform/data.py
ndimreg/transform/transformation.py
ndimreg/transform/types.py
ndimreg/utils/__init__.py
ndimreg/utils/arrays.py
ndimreg/utils/dataframes.py
ndimreg/utils/diffs.py
ndimreg/utils/fft.py
ndimreg/utils/image.py
ndimreg/utils/image_operations.py
ndimreg/utils/logging.py
ndimreg/utils/memory_log.py
ndimreg/utils/misc.py
ndimreg/utils/plot_images.py
ndimreg/utils/timer.py
ndimreg/utils/transformation_generators.py
ndimreg-0.2.0.dist-info/METADATA
ndimreg-0.2.0.dist-info/WHEEL
ndimreg-0.2.0.dist-info/entry_points.txt
ndimreg-0.2.0.dist-info/licenses/LICENSE
ndimreg-0.2.0.dist-info/RECORD
