Metadata-Version: 2.4
Name: ndimreg
Version: 0.2.0
Summary: N-dimensional image registrations
Project-URL: Homepage, https://github.com/jnk22/ndimreg
Project-URL: Repository, https://github.com/jnk22/ndimreg
Project-URL: Documentation, https://ndimreg.readthedocs.io
Author-email: jnk22 <jannik.schaefer@inbox-online.de>
License-Expression: MIT
License-File: LICENSE
Keywords: 2d,3d,fft,image,ppft,registration
Classifier: Development Status :: 2 - Pre-Alpha
Classifier: Intended Audience :: Developers
Classifier: Intended Audience :: Science/Research
Classifier: License :: OSI Approved :: MIT License
Classifier: Natural Language :: English
Classifier: Programming Language :: Python :: 3
Classifier: Programming Language :: Python :: 3 :: Only
Classifier: Programming Language :: Python :: 3.10
Classifier: Programming Language :: Python :: 3.11
Classifier: Programming Language :: Python :: 3.12
Classifier: Topic :: Scientific/Engineering
Classifier: Topic :: Scientific/Engineering :: Image Processing
Classifier: Topic :: Scientific/Engineering :: Visualization
Requires-Python: <4,>=3.10
Requires-Dist: array-api-compat>=1.9
Requires-Dist: cachetools>=5.5.0
Requires-Dist: cyclopts>=3.2
Requires-Dist: imreg-dft
Requires-Dist: loguru
Requires-Dist: matplotlib
Requires-Dist: mpire>=2.10.2
Requires-Dist: napari
Requires-Dist: numpy
Requires-Dist: polars>=1.11.0
Requires-Dist: ppft-py>=0.1.0
Requires-Dist: py-cpuinfo>=9.0.0
Requires-Dist: pyqt6
Requires-Dist: pytransform3d>=3.8.0
Requires-Dist: scikit-image
Requires-Dist: scipy<2
Requires-Dist: tqdm
Requires-Dist: typing-extensions>=4.12.2
Requires-Dist: tzlocal>=5.2
Provides-Extra: cuda11
Requires-Dist: cucim-cu11>=24.10.0; extra == 'cuda11'
Requires-Dist: cupy-cuda11x>=13.3.0; extra == 'cuda11'
Provides-Extra: cuda12
Requires-Dist: cucim-cu12>=24.10.0; extra == 'cuda12'
Requires-Dist: cupy-cuda12x>=13.3.0; extra == 'cuda12'
Provides-Extra: mkl
Requires-Dist: mkl-fft>=1.3.11; extra == 'mkl'
Requires-Dist: mkl-service>=2.4.2; extra == 'mkl'
Provides-Extra: pyfftw
Requires-Dist: pyfftw>=0.15.0; extra == 'pyfftw'
Provides-Extra: rocm-4-3
Requires-Dist: cucim>=23.10.0; extra == 'rocm-4-3'
Requires-Dist: cupy-rocm-4-3<13; extra == 'rocm-4-3'
Provides-Extra: rocm-5-0
Requires-Dist: cucim>=23.10.0; extra == 'rocm-5-0'
Requires-Dist: cupy-rocm-5-0<13; extra == 'rocm-5-0'
